hashidstr.py
hashidstr-1.3.3.dist-info/LICENSE
hashidstr-1.3.3.dist-info/WHEEL
hashidstr-1.3.3.dist-info/METADATA
hashidstr-1.3.3.dist-info/RECORD
