Metadata-Version: 2.1
Name: hashidstr
Version: 1.3.3
Summary: Implements the hashids algorithm in python with support of string.
Home-page: https://hashids.org/python/
Author: Shubham Rath
Author-email: hello@shubhamrath.dev
Requires-Python: >=2.7
Classifier: License :: OSI Approved :: MIT License
Classifier: Programming Language :: Python :: 2
Classifier: Programming Language :: Python :: 2.7
Classifier: Programming Language :: Python :: 3
Classifier: Programming Language :: Python :: 3.5
Classifier: Programming Language :: Python :: 3.6
Classifier: Programming Language :: Python :: 3.7
Classifier: Programming Language :: Python :: 3.8
Requires-Dist: pytest >=2.1.0 ; extra == "test"
Provides-Extra: test
